{
	"info": {
		"_postman_id": "10cb9c74-1e2a-425b-b439-377f9ed7671f",
		"name": "API equinox",
		"schema": "https://schema.getpostman.com/json/collection/v2.1.0/collection.json"
	},
	"item": [
		{
			"name": "Rol",
			"item": [
				{
					"name": "Listar los roles",
					"request": {
						"method": "GET",
						"header": [],
						"url": {
							"raw": "{{base_url}}rol",
							"host": [
								"{{base_url}}rol"
							]
						}
					},
					"response": []
				},
				{
					"name": "Consultar un rol",
					"request": {
						"method": "GET",
						"header": [],
						"url": {
							"raw": "{{base_url}}rol/2",
							"host": [
								"{{base_url}}rol"
							],
							"path": [
								"2"
							]
						}
					},
					"response": []
				}
			],
			"protocolProfileBehavior": {}
		},
		{
			"name": "User",
			"item": [
				{
					"name": "Listar los usuarios",
					"request": {
						"auth": {
							"type": "bearer",
							"bearer": [
								{
									"key": "token",
									"value": "{{token}}",
									"type": "string"
								}
							]
						},
						"method": "GET",
						"header": [],
						"url": {
							"raw": "{{base_url}}user",
							"host": [
								"{{base_url}}user"
							]
						}
					},
					"response": []
				},
				{
					"name": "Consultar un usuario",
					"request": {
						"method": "GET",
						"header": [],
						"url": {
							"raw": "{{base_url}}user/3",
							"host": [
								"{{base_url}}user"
							],
							"path": [
								"3"
							]
						}
					},
					"response": []
				},
				{
					"name": "Registrar usuario",
					"request": {
						"auth": {
							"type": "bearer",
							"bearer": [
								{
									"key": "token",
									"value": "{{token}}",
									"type": "string"
								}
							]
						},
						"method": "POST",
						"header": [],
						"body": {
							"mode": "urlencoded",
							"urlencoded": [
								{
									"key": "name",
									"value": "Usuario de prueba 1",
									"type": "text"
								},
								{
									"key": "email",
									"value": "1010@gmail.com",
									"type": "text"
								},
								{
									"key": "password",
									"value": "123456",
									"type": "text"
								},
								{
									"key": "estado",
									"value": "1",
									"type": "text"
								},
								{
									"key": "rol_id",
									"value": "1",
									"type": "text"
								}
							],
							"options": {
								"urlencoded": {}
							}
						},
						"url": {
							"raw": "{{base_url}}auth/register",
							"host": [
								"{{base_url}}auth"
							],
							"path": [
								"register"
							]
						}
					},
					"response": []
				},
				{
					"name": "Login",
					"request": {
						"auth": {
							"type": "bearer",
							"bearer": [
								{
									"key": "token",
									"value": "{{token}}",
									"type": "string"
								}
							]
						},
						"method": "POST",
						"header": [],
						"body": {
							"mode": "urlencoded",
							"urlencoded": [
								{
									"key": "email",
									"value": "jm@gmail.com",
									"type": "text"
								},
								{
									"key": "password",
									"value": "123456",
									"type": "text"
								}
							]
						},
						"url": {
							"raw": "{{base_url}}auth/login",
							"host": [
								"{{base_url}}auth"
							],
							"path": [
								"login"
							]
						}
					},
					"response": []
				},
				{
					"name": "Logout",
					"request": {
						"auth": {
							"type": "bearer",
							"bearer": [
								{
									"key": "token",
									"value": "{{token}}",
									"type": "string"
								}
							]
						},
						"method": "POST",
						"header": [],
						"url": {
							"raw": "{{base_url}}auth/logout",
							"host": [
								"{{base_url}}auth"
							],
							"path": [
								"logout"
							]
						}
					},
					"response": []
				}
			],
			"protocolProfileBehavior": {}
		},
		{
			"name": "Personal",
			"item": [
				{
					"name": "Listar el personal",
					"request": {
						"auth": {
							"type": "bearer",
							"bearer": [
								{
									"key": "token",
									"value": "{{token}}",
									"type": "string"
								}
							]
						},
						"method": "GET",
						"header": [],
						"url": {
							"raw": "{{base_url}}personal/all/",
							"host": [
								"{{base_url}}personal"
							],
							"path": [
								"all",
								""
							]
						}
					},
					"response": []
				},
				{
					"name": "Consultar un personal",
					"request": {
						"auth": {
							"type": "bearer",
							"bearer": [
								{
									"key": "token",
									"value": "{{token}}",
									"type": "string"
								}
							]
						},
						"method": "GET",
						"header": [],
						"url": {
							"raw": "{{base_url}}personal/1/",
							"host": [
								"{{base_url}}personal"
							],
							"path": [
								"1",
								""
							]
						}
					},
					"response": []
				},
				{
					"name": "Index de personal",
					"request": {
						"auth": {
							"type": "bearer",
							"bearer": [
								{
									"key": "token",
									"value": "{{token}}",
									"type": "string"
								}
							]
						},
						"method": "GET",
						"header": [],
						"url": {
							"raw": "{{base_url}}personal/",
							"host": [
								"{{base_url}}personal"
							],
							"path": [
								""
							]
						}
					},
					"response": []
				},
				{
					"name": "Crear personal",
					"request": {
						"auth": {
							"type": "bearer",
							"bearer": [
								{
									"key": "token",
									"value": "{{token}}",
									"type": "string"
								}
							]
						},
						"method": "POST",
						"header": [],
						"body": {
							"mode": "urlencoded",
							"urlencoded": [
								{
									"key": "nombre",
									"value": "Nayely",
									"type": "text"
								},
								{
									"key": "apellido",
									"value": "Sandi",
									"type": "text"
								},
								{
									"key": "correo",
									"value": "nsm@gmail.com",
									"type": "text"
								},
								{
									"key": "telefono",
									"value": "60124569",
									"type": "text"
								},
								{
									"key": "estado",
									"value": "true",
									"type": "text"
								},
								{
									"key": "vehiculo_id",
									"value": "2",
									"type": "text"
								}
							]
						},
						"url": {
							"raw": "{{base_url}}store",
							"host": [
								"{{base_url}}store"
							]
						}
					},
					"response": []
				}
			],
			"protocolProfileBehavior": {}
		},
		{
			"name": "Vehiculo",
			"item": [
				{
					"name": "Lista de vehiculos",
					"protocolProfileBehavior": {
						"disableBodyPruning": true
					},
					"request": {
						"method": "GET",
						"header": [],
						"body": {
							"mode": "urlencoded",
							"urlencoded": [
								{
									"key": "name",
									"value": "Prueba de usuario",
									"type": "text"
								},
								{
									"key": "email",
									"value": "1324@gmail.com",
									"type": "text"
								},
								{
									"key": "password",
									"value": "13241324",
									"type": "text"
								},
								{
									"key": "estado",
									"value": "1",
									"type": "text"
								},
								{
									"key": "rol_id",
									"value": "2",
									"type": "text"
								}
							]
						},
						"url": {
							"raw": "{{base_url}}vehiculo/",
							"host": [
								"{{base_url}}vehiculo"
							],
							"path": [
								""
							]
						}
					},
					"response": []
				},
				{
					"name": "Consultar un vehiculo",
					"request": {
						"method": "GET",
						"header": [],
						"url": {
							"raw": "{{base_url}}vehiculo/3",
							"host": [
								"{{base_url}}vehiculo"
							],
							"path": [
								"3"
							]
						}
					},
					"response": []
				}
			],
			"protocolProfileBehavior": {}
		},
		{
			"name": "Pedido",
			"item": [
				{
					"name": "Listar pedidos",
					"request": {
						"auth": {
							"type": "bearer",
							"bearer": [
								{
									"key": "token",
									"value": "{{token}}",
									"type": "string"
								}
							]
						},
						"method": "GET",
						"header": [],
						"url": {
							"raw": "{{base_url}}pedido/all/",
							"host": [
								"{{base_url}}pedido"
							],
							"path": [
								"all",
								""
							]
						}
					},
					"response": []
				},
				{
					"name": "Consultar un pedido",
					"request": {
						"auth": {
							"type": "bearer",
							"bearer": [
								{
									"key": "token",
									"value": "{{token}}",
									"type": "string"
								}
							]
						},
						"method": "GET",
						"header": [],
						"url": {
							"raw": "{{base_url}}pedido/1/",
							"host": [
								"{{base_url}}pedido"
							],
							"path": [
								"1",
								""
							]
						}
					},
					"response": []
				},
				{
					"name": "Index de pedidos",
					"request": {
						"auth": {
							"type": "bearer",
							"bearer": [
								{
									"key": "token",
									"value": "{{token}}",
									"type": "string"
								}
							]
						},
						"method": "GET",
						"header": [],
						"url": {
							"raw": "{{base_url}}pedido/",
							"host": [
								"{{base_url}}pedido"
							],
							"path": [
								""
							]
						}
					},
					"response": []
				},
				{
					"name": "Crear un pedido",
					"request": {
						"auth": {
							"type": "bearer",
							"bearer": [
								{
									"key": "token",
									"value": "{{token}}",
									"type": "string"
								}
							]
						},
						"method": "POST",
						"header": [],
						"body": {
							"mode": "urlencoded",
							"urlencoded": [
								{
									"key": "cedula_cliente",
									"value": "201230852",
									"type": "text"
								},
								{
									"key": "nombre_completo_cliente",
									"value": "Berlín Gonzáles",
									"type": "text"
								},
								{
									"key": "telefono_cliente",
									"value": "25641023",
									"type": "text"
								},
								{
									"key": "tipo_pedido",
									"value": "Pasa a retirar",
									"type": "text"
								},
								{
									"key": "fecha",
									"value": "2020-10-21",
									"type": "text"
								},
								{
									"key": "direccion",
									"value": "Frente al Maxi Palí de Grecia",
									"type": "text"
								},
								{
									"key": "subtotal",
									"value": "450000",
									"type": "text"
								},
								{
									"key": "impuesto",
									"value": "58500",
									"type": "text"
								},
								{
									"key": "envio",
									"value": "0",
									"type": "text"
								},
								{
									"key": "total",
									"value": "508500",
									"type": "text"
								},
								{
									"key": "estado",
									"value": "pendiente",
									"type": "text"
								},
								{
									"key": "provincia_id",
									"value": "2",
									"type": "text"
								},
								{
									"key": "personal_id",
									"value": "1",
									"type": "text"
								}
							]
						},
						"url": {
							"raw": "{{base_url}}pedido/storeapi",
							"host": [
								"{{base_url}}pedido"
							],
							"path": [
								"storeapi"
							]
						}
					},
					"response": []
				},
				{
					"name": "Crear un detalle del pedido",
					"request": {
						"auth": {
							"type": "bearer",
							"bearer": [
								{
									"key": "token",
									"value": "{{token}}",
									"type": "string"
								}
							]
						},
						"method": "POST",
						"header": [],
						"body": {
							"mode": "urlencoded",
							"urlencoded": [
								{
									"key": "pedido_id",
									"value": "5",
									"type": "text"
								},
								{
									"key": "producto_id",
									"value": "1",
									"type": "text"
								},
								{
									"key": "cantidad",
									"value": "1",
									"type": "text"
								},
								{
									"key": "total",
									"value": "450000",
									"type": "text"
								}
							]
						},
						"url": {
							"raw": "{{base_url}}detallepedido",
							"host": [
								"{{base_url}}detallepedido"
							]
						}
					},
					"response": []
				}
			],
			"protocolProfileBehavior": {}
		},
		{
			"name": "Producto",
			"item": [
				{
					"name": "Listar productos",
					"request": {
						"auth": {
							"type": "bearer",
							"bearer": [
								{
									"key": "token",
									"value": "{{token}}",
									"type": "string"
								}
							]
						},
						"method": "GET",
						"header": [],
						"url": {
							"raw": "{{base_url}}producto/all",
							"host": [
								"{{base_url}}producto"
							],
							"path": [
								"all"
							]
						}
					},
					"response": []
				},
				{
					"name": "Consultar un producto",
					"request": {
						"auth": {
							"type": "bearer",
							"bearer": [
								{
									"key": "token",
									"value": "{{token}}",
									"type": "string"
								}
							]
						},
						"method": "GET",
						"header": [],
						"url": {
							"raw": "{{base_url}}producto/2",
							"host": [
								"{{base_url}}producto"
							],
							"path": [
								"2"
							]
						}
					},
					"response": []
				},
				{
					"name": "Index de productos",
					"request": {
						"auth": {
							"type": "bearer",
							"bearer": [
								{
									"key": "token",
									"value": "{{token}}",
									"type": "string"
								}
							]
						},
						"method": "GET",
						"header": [],
						"url": {
							"raw": "{{base_url}}producto/",
							"host": [
								"{{base_url}}producto"
							],
							"path": [
								""
							]
						}
					},
					"response": []
				}
			],
			"protocolProfileBehavior": {}
		}
	],
	"protocolProfileBehavior": {}
}